{"word":"çiçek","pos":"noun","senses":[{"glosses":["flower"],"examples":[{"text":"çiçek sulama kabı","translation":"flower watering vessel"}]},{"glosses":["blossom"]},{"glosses":["smallpox, variola"],"synonyms":["su çiçeği"]},{"glosses":["efflorescence"]},{"glosses":["a female given name"]}],"pronunciation":"/t͡ʃiˈt͡ʃec/","etymology":"From Ottoman Turkish چیچك (çiçek), from Proto-Turkic *čeček. See Bashkir сәскә (səskə) for further cognates.","forms":[{"form":"çiçeği","tags":["accusative","definite"]},{"form":"çiçekler","tags":["plural"]},{"form":"no-table-tags","tags":["table-tags"]},{"form":"tr-infl-noun-c","tags":["inflection-template"]},{"form":"çiçek","tags":["nominative","singular"]},{"form":"çiçekler","tags":["nominative","plural"]},{"form":"çiçeği","tags":["accusative","definite","singular"]},{"form":"çiçekleri","tags":["accusative","definite","plural"]},{"form":"çiçeğe","tags":["dative","singular"]},{"form":"çiçeklere","tags":["dative","plural"]},{"form":"çiçekte","tags":["locative","singular"]},{"form":"çiçeklerde","tags":["locative","plural"]},{"form":"çiçekten","tags":["ablative","singular"]},{"form":"çiçeklerden","tags":["ablative","plural"]},{"form":"çiçeğin","tags":["genitive","singular"]},{"form":"çiçeklerin","tags":["genitive","plural"]},{"form":"no-table-tags","tags":["table-tags"]},{"form":"tr-infl-noun-c","tags":["inflection-template"]},{"form":"çiçeğim","tags":["first-person","nominative","singular"]},{"form":"çiçeklerim","tags":["first-person","nominative","singular"]},{"form":"çiçeğin","tags":["nominative","second-person","singular"]},{"form":"çiçeklerin","tags":["nominative","second-person","singular"]},{"form":"çiçeği","tags":["nominative","singular","third-person"]},{"form":"çiçekleri","tags":["nominative","singular","third-person"]},{"form":"çiçeğimiz","tags":["first-person","nominative","plural"]},{"form":"çiçeklerimiz","tags":["first-person","nominative","plural"]},{"form":"çiçeğiniz","tags":["nominative","plural","second-person"]},{"form":"çiçekleriniz","tags":["nominative","plural","second-person"]},{"form":"çiçekleri","tags":["nominative","plural","third-person"]},{"form":"çiçeğimi","tags":["accusative","definite","first-person","singular"]},{"form":"çiçeklerimi","tags":["accusative","definite","first-person","singular"]},{"form":"çiçeğini","tags":["accusative","definite","second-person","singular"]},{"form":"çiçeklerini","tags":["accusative","definite","second-person","singular"]},{"form":"çiçeğini","tags":["accusative","definite","singular","third-person"]},{"form":"çiçeklerini","tags":["accusative","definite","singular","third-person"]},{"form":"çiçeğimizi","tags":["accusative","definite","first-person","plural"]},{"form":"çiçeklerimizi","tags":["accusative","definite","first-person","plural"]},{"form":"çiçeğinizi","tags":["accusative","definite","plural","second-person"]},{"form":"çiçeklerinizi","tags":["accusative","definite","plural","second-person"]},{"form":"çiçeklerini","tags":["accusative","definite","plural","third-person"]},{"form":"çiçeğime","tags":["dative","first-person","singular"]},{"form":"çiçeklerime","tags":["dative","first-person","singular"]},{"form":"çiçeğine","tags":["dative","second-person","singular"]},{"form":"çiçeklerine","tags":["dative","second-person","singular"]},{"form":"çiçeğine","tags":["dative","singular","third-person"]},{"form":"çiçeklerine","tags":["dative","singular","third-person"]},{"form":"çiçeğimize","tags":["dative","first-person","plural"]},{"form":"çiçeklerimize","tags":["dative","first-person","plural"]},{"form":"çiçeğinize","tags":["dative","plural","second-person"]},{"form":"çiçeklerinize","tags":["dative","plural","second-person"]},{"form":"çiçeklerine","tags":["dative","plural","third-person"]},{"form":"çiçeğimde","tags":["first-person","locative","singular"]},{"form":"çiçeklerimde","tags":["first-person","locative","singular"]},{"form":"çiçeğinde","tags":["locative","second-person","singular"]},{"form":"çiçeklerinde","tags":["locative","second-person","singular"]},{"form":"çiçeğinde","tags":["locative","singular","third-person"]},{"form":"çiçeklerinde","tags":["locative","singular","third-person"]},{"form":"çiçeğimizde","tags":["first-person","locative","plural"]},{"form":"çiçeklerimizde","tags":["first-person","locative","plural"]},{"form":"çiçeğinizde","tags":["locative","plural","second-person"]},{"form":"çiçeklerinizde","tags":["locative","plural","second-person"]},{"form":"çiçeklerinde","tags":["locative","plural","third-person"]},{"form":"çiçeğimden","tags":["ablative","first-person","singular"]},{"form":"çiçeklerimden","tags":["ablative","first-person","singular"]},{"form":"çiçeğinden","tags":["ablative","second-person","singular"]},{"form":"çiçeklerinden","tags":["ablative","second-person","singular"]},{"form":"çiçeğinden","tags":["ablative","singular","third-person"]},{"form":"çiçeklerinden","tags":["ablative","singular","third-person"]},{"form":"çiçeğimizden","tags":["ablative","first-person","plural"]},{"form":"çiçeklerimizden","tags":["ablative","first-person","plural"]},{"form":"çiçeğinizden","tags":["ablative","plural","second-person"]},{"form":"çiçeklerinizden","tags":["ablative","plural","second-person"]},{"form":"çiçeklerinden","tags":["ablative","plural","third-person"]},{"form":"çiçeğimin","tags":["first-person","genitive","singular"]},{"form":"çiçeklerimin","tags":["first-person","genitive","singular"]},{"form":"çiçeğinin","tags":["genitive","second-person","singular"]},{"form":"çiçeklerinin","tags":["genitive","second-person","singular"]},{"form":"çiçeğinin","tags":["genitive","singular","third-person"]},{"form":"çiçeklerinin","tags":["genitive","singular","third-person"]},{"form":"çiçeğimizin","tags":["first-person","genitive","plural"]},{"form":"çiçeklerimizin","tags":["first-person","genitive","plural"]},{"form":"çiçeğinizin","tags":["genitive","plural","second-person"]},{"form":"çiçeklerinizin","tags":["genitive","plural","second-person"]},{"form":"çiçeklerinin","tags":["genitive","plural","third-person"]}]}