{"word":"aksatma","pos":"noun","senses":[{"glosses":["verbal noun of aksatmak"],"tags":["form-of","noun-from-verb"]},{"glosses":["second-person singular negative imperative of aksatmak"],"tags":["form-of","imperative","negative","second-person","singular"]}],"forms":[{"form":"aksatmayı","tags":["accusative","definite"]},{"form":"aksatmalar","tags":["plural"]},{"form":"no-table-tags","tags":["table-tags"]},{"form":"tr-infl-noun-v","tags":["inflection-template"]},{"form":"aksatma","tags":["nominative","singular"]},{"form":"aksatmalar","tags":["nominative","plural"]},{"form":"aksatmayı","tags":["accusative","definite","singular"]},{"form":"aksatmaları","tags":["accusative","definite","plural"]},{"form":"aksatmaya","tags":["dative","singular"]},{"form":"aksatmalara","tags":["dative","plural"]},{"form":"aksatmada","tags":["locative","singular"]},{"form":"aksatmalarda","tags":["locative","plural"]},{"form":"aksatmadan","tags":["ablative","singular"]},{"form":"aksatmalardan","tags":["ablative","plural"]},{"form":"aksatmanın","tags":["genitive","singular"]},{"form":"aksatmaların","tags":["genitive","plural"]},{"form":"no-table-tags","tags":["table-tags"]},{"form":"tr-infl-noun-v","tags":["inflection-template"]},{"form":"aksatmam","tags":["first-person","nominative","singular"]},{"form":"aksatmalarım","tags":["first-person","nominative","singular"]},{"form":"aksatman","tags":["nominative","second-person","singular"]},{"form":"aksatmaların","tags":["nominative","second-person","singular"]},{"form":"aksatması","tags":["nominative","singular","third-person"]},{"form":"aksatmaları","tags":["nominative","singular","third-person"]},{"form":"aksatmamız","tags":["first-person","nominative","plural"]},{"form":"aksatmalarımız","tags":["first-person","nominative","plural"]},{"form":"aksatmanız","tags":["nominative","plural","second-person"]},{"form":"aksatmalarınız","tags":["nominative","plural","second-person"]},{"form":"aksatmaları","tags":["nominative","plural","third-person"]},{"form":"aksatmamı","tags":["accusative","definite","first-person","singular"]},{"form":"aksatmalarımı","tags":["accusative","definite","first-person","singular"]},{"form":"aksatmanı","tags":["accusative","definite","second-person","singular"]},{"form":"aksatmalarını","tags":["accusative","definite","second-person","singular"]},{"form":"aksatmasını","tags":["accusative","definite","singular","third-person"]},{"form":"aksatmalarını","tags":["accusative","definite","singular","third-person"]},{"form":"aksatmamızı","tags":["accusative","definite","first-person","plural"]},{"form":"aksatmalarımızı","tags":["accusative","definite","first-person","plural"]},{"form":"aksatmanızı","tags":["accusative","definite","plural","second-person"]},{"form":"aksatmalarınızı","tags":["accusative","definite","plural","second-person"]},{"form":"aksatmalarını","tags":["accusative","definite","plural","third-person"]},{"form":"aksatmama","tags":["dative","first-person","singular"]},{"form":"aksatmalarıma","tags":["dative","first-person","singular"]},{"form":"aksatmana","tags":["dative","second-person","singular"]},{"form":"aksatmalarına","tags":["dative","second-person","singular"]},{"form":"aksatmasına","tags":["dative","singular","third-person"]},{"form":"aksatmalarına","tags":["dative","singular","third-person"]},{"form":"aksatmamıza","tags":["dative","first-person","plural"]},{"form":"aksatmalarımıza","tags":["dative","first-person","plural"]},{"form":"aksatmanıza","tags":["dative","plural","second-person"]},{"form":"aksatmalarınıza","tags":["dative","plural","second-person"]},{"form":"aksatmalarına","tags":["dative","plural","third-person"]},{"form":"aksatmamda","tags":["first-person","locative","singular"]},{"form":"aksatmalarımda","tags":["first-person","locative","singular"]},{"form":"aksatmanda","tags":["locative","second-person","singular"]},{"form":"aksatmalarında","tags":["locative","second-person","singular"]},{"form":"aksatmasında","tags":["locative","singular","third-person"]},{"form":"aksatmalarında","tags":["locative","singular","third-person"]},{"form":"aksatmamızda","tags":["first-person","locative","plural"]},{"form":"aksatmalarımızda","tags":["first-person","locative","plural"]},{"form":"aksatmanızda","tags":["locative","plural","second-person"]},{"form":"aksatmalarınızda","tags":["locative","plural","second-person"]},{"form":"aksatmalarında","tags":["locative","plural","third-person"]},{"form":"aksatmamdan","tags":["ablative","first-person","singular"]},{"form":"aksatmalarımdan","tags":["ablative","first-person","singular"]},{"form":"aksatmandan","tags":["ablative","second-person","singular"]},{"form":"aksatmalarından","tags":["ablative","second-person","singular"]},{"form":"aksatmasından","tags":["ablative","singular","third-person"]},{"form":"aksatmalarından","tags":["ablative","singular","third-person"]},{"form":"aksatmamızdan","tags":["ablative","first-person","plural"]},{"form":"aksatmalarımızdan","tags":["ablative","first-person","plural"]},{"form":"aksatmanızdan","tags":["ablative","plural","second-person"]},{"form":"aksatmalarınızdan","tags":["ablative","plural","second-person"]},{"form":"aksatmalarından","tags":["ablative","plural","third-person"]},{"form":"aksatmamın","tags":["first-person","genitive","singular"]},{"form":"aksatmalarımın","tags":["first-person","genitive","singular"]},{"form":"aksatmanın","tags":["genitive","second-person","singular"]},{"form":"aksatmalarının","tags":["genitive","second-person","singular"]},{"form":"aksatmasının","tags":["genitive","singular","third-person"]},{"form":"aksatmalarının","tags":["genitive","singular","third-person"]},{"form":"aksatmamızın","tags":["first-person","genitive","plural"]},{"form":"aksatmalarımızın","tags":["first-person","genitive","plural"]},{"form":"aksatmanızın","tags":["genitive","plural","second-person"]},{"form":"aksatmalarınızın","tags":["genitive","plural","second-person"]},{"form":"aksatmalarının","tags":["genitive","plural","third-person"]}]}