{"word":"karşılaştırma","pos":"noun","senses":[{"glosses":["verbal noun of karşılaştırmak: comparison"],"tags":["form-of","noun-from-verb"]},{"glosses":["second-person singular negative imperative of karşılaştırmak"],"tags":["form-of","imperative","negative","second-person","singular"]}],"forms":[{"form":"karşılaştırmayı","tags":["accusative","definite"]},{"form":"karşılaştırmalar","tags":["plural"]},{"form":"no-table-tags","tags":["table-tags"]},{"form":"tr-infl-noun-v","tags":["inflection-template"]},{"form":"karşılaştırma","tags":["nominative","singular"]},{"form":"karşılaştırmalar","tags":["nominative","plural"]},{"form":"karşılaştırmayı","tags":["accusative","definite","singular"]},{"form":"karşılaştırmaları","tags":["accusative","definite","plural"]},{"form":"karşılaştırmaya","tags":["dative","singular"]},{"form":"karşılaştırmalara","tags":["dative","plural"]},{"form":"karşılaştırmada","tags":["locative","singular"]},{"form":"karşılaştırmalarda","tags":["locative","plural"]},{"form":"karşılaştırmadan","tags":["ablative","singular"]},{"form":"karşılaştırmalardan","tags":["ablative","plural"]},{"form":"karşılaştırmanın","tags":["genitive","singular"]},{"form":"karşılaştırmaların","tags":["genitive","plural"]},{"form":"no-table-tags","tags":["table-tags"]},{"form":"tr-infl-noun-v","tags":["inflection-template"]},{"form":"karşılaştırmam","tags":["first-person","nominative","singular"]},{"form":"karşılaştırmalarım","tags":["first-person","nominative","singular"]},{"form":"karşılaştırman","tags":["nominative","second-person","singular"]},{"form":"karşılaştırmaların","tags":["nominative","second-person","singular"]},{"form":"karşılaştırması","tags":["nominative","singular","third-person"]},{"form":"karşılaştırmaları","tags":["nominative","singular","third-person"]},{"form":"karşılaştırmamız","tags":["first-person","nominative","plural"]},{"form":"karşılaştırmalarımız","tags":["first-person","nominative","plural"]},{"form":"karşılaştırmanız","tags":["nominative","plural","second-person"]},{"form":"karşılaştırmalarınız","tags":["nominative","plural","second-person"]},{"form":"karşılaştırmaları","tags":["nominative","plural","third-person"]},{"form":"karşılaştırmamı","tags":["accusative","definite","first-person","singular"]},{"form":"karşılaştırmalarımı","tags":["accusative","definite","first-person","singular"]},{"form":"karşılaştırmanı","tags":["accusative","definite","second-person","singular"]},{"form":"karşılaştırmalarını","tags":["accusative","definite","second-person","singular"]},{"form":"karşılaştırmasını","tags":["accusative","definite","singular","third-person"]},{"form":"karşılaştırmalarını","tags":["accusative","definite","singular","third-person"]},{"form":"karşılaştırmamızı","tags":["accusative","definite","first-person","plural"]},{"form":"karşılaştırmalarımızı","tags":["accusative","definite","first-person","plural"]},{"form":"karşılaştırmanızı","tags":["accusative","definite","plural","second-person"]},{"form":"karşılaştırmalarınızı","tags":["accusative","definite","plural","second-person"]},{"form":"karşılaştırmalarını","tags":["accusative","definite","plural","third-person"]},{"form":"karşılaştırmama","tags":["dative","first-person","singular"]},{"form":"karşılaştırmalarıma","tags":["dative","first-person","singular"]},{"form":"karşılaştırmana","tags":["dative","second-person","singular"]},{"form":"karşılaştırmalarına","tags":["dative","second-person","singular"]},{"form":"karşılaştırmasına","tags":["dative","singular","third-person"]},{"form":"karşılaştırmalarına","tags":["dative","singular","third-person"]},{"form":"karşılaştırmamıza","tags":["dative","first-person","plural"]},{"form":"karşılaştırmalarımıza","tags":["dative","first-person","plural"]},{"form":"karşılaştırmanıza","tags":["dative","plural","second-person"]},{"form":"karşılaştırmalarınıza","tags":["dative","plural","second-person"]},{"form":"karşılaştırmalarına","tags":["dative","plural","third-person"]},{"form":"karşılaştırmamda","tags":["first-person","locative","singular"]},{"form":"karşılaştırmalarımda","tags":["first-person","locative","singular"]},{"form":"karşılaştırmanda","tags":["locative","second-person","singular"]},{"form":"karşılaştırmalarında","tags":["locative","second-person","singular"]},{"form":"karşılaştırmasında","tags":["locative","singular","third-person"]},{"form":"karşılaştırmalarında","tags":["locative","singular","third-person"]},{"form":"karşılaştırmamızda","tags":["first-person","locative","plural"]},{"form":"karşılaştırmalarımızda","tags":["first-person","locative","plural"]},{"form":"karşılaştırmanızda","tags":["locative","plural","second-person"]},{"form":"karşılaştırmalarınızda","tags":["locative","plural","second-person"]},{"form":"karşılaştırmalarında","tags":["locative","plural","third-person"]},{"form":"karşılaştırmamdan","tags":["ablative","first-person","singular"]},{"form":"karşılaştırmalarımdan","tags":["ablative","first-person","singular"]},{"form":"karşılaştırmandan","tags":["ablative","second-person","singular"]},{"form":"karşılaştırmalarından","tags":["ablative","second-person","singular"]},{"form":"karşılaştırmasından","tags":["ablative","singular","third-person"]},{"form":"karşılaştırmalarından","tags":["ablative","singular","third-person"]},{"form":"karşılaştırmamızdan","tags":["ablative","first-person","plural"]},{"form":"karşılaştırmalarımızdan","tags":["ablative","first-person","plural"]},{"form":"karşılaştırmanızdan","tags":["ablative","plural","second-person"]},{"form":"karşılaştırmalarınızdan","tags":["ablative","plural","second-person"]},{"form":"karşılaştırmalarından","tags":["ablative","plural","third-person"]},{"form":"karşılaştırmamın","tags":["first-person","genitive","singular"]},{"form":"karşılaştırmalarımın","tags":["first-person","genitive","singular"]},{"form":"karşılaştırmanın","tags":["genitive","second-person","singular"]},{"form":"karşılaştırmalarının","tags":["genitive","second-person","singular"]},{"form":"karşılaştırmasının","tags":["genitive","singular","third-person"]},{"form":"karşılaştırmalarının","tags":["genitive","singular","third-person"]},{"form":"karşılaştırmamızın","tags":["first-person","genitive","plural"]},{"form":"karşılaştırmalarımızın","tags":["first-person","genitive","plural"]},{"form":"karşılaştırmanızın","tags":["genitive","plural","second-person"]},{"form":"karşılaştırmalarınızın","tags":["genitive","plural","second-person"]},{"form":"karşılaştırmalarının","tags":["genitive","plural","third-person"]}]}