{"word":"nimet","pos":"noun","senses":[{"glosses":["blessing"]},{"glosses":["a female given name from Arabic"]}],"pronunciation":"/niːmet/","etymology":"Inherited from Ottoman Turkish نعمت, from Arabic نِعْمَة (niʕma).","forms":[{"form":"nimeti","tags":["accusative","definite"]},{"form":"nimetler","tags":["plural"]},{"form":"no-table-tags","tags":["table-tags"]},{"form":"tr-infl-noun-c","tags":["inflection-template"]},{"form":"nimet","tags":["nominative","singular"]},{"form":"nimetler","tags":["nominative","plural"]},{"form":"nimeti","tags":["accusative","definite","singular"]},{"form":"nimetleri","tags":["accusative","definite","plural"]},{"form":"nimete","tags":["dative","singular"]},{"form":"nimetlere","tags":["dative","plural"]},{"form":"nimette","tags":["locative","singular"]},{"form":"nimetlerde","tags":["locative","plural"]},{"form":"nimetten","tags":["ablative","singular"]},{"form":"nimetlerden","tags":["ablative","plural"]},{"form":"nimetin","tags":["genitive","singular"]},{"form":"nimetlerin","tags":["genitive","plural"]},{"form":"no-table-tags","tags":["table-tags"]},{"form":"tr-infl-noun-c","tags":["inflection-template"]},{"form":"nimetim","tags":["first-person","nominative","singular"]},{"form":"nimetlerim","tags":["first-person","nominative","singular"]},{"form":"nimetin","tags":["nominative","second-person","singular"]},{"form":"nimetlerin","tags":["nominative","second-person","singular"]},{"form":"nimeti","tags":["nominative","singular","third-person"]},{"form":"nimetleri","tags":["nominative","singular","third-person"]},{"form":"nimetimiz","tags":["first-person","nominative","plural"]},{"form":"nimetlerimiz","tags":["first-person","nominative","plural"]},{"form":"nimetiniz","tags":["nominative","plural","second-person"]},{"form":"nimetleriniz","tags":["nominative","plural","second-person"]},{"form":"nimetleri","tags":["nominative","plural","third-person"]},{"form":"nimetimi","tags":["accusative","definite","first-person","singular"]},{"form":"nimetlerimi","tags":["accusative","definite","first-person","singular"]},{"form":"nimetini","tags":["accusative","definite","second-person","singular"]},{"form":"nimetlerini","tags":["accusative","definite","second-person","singular"]},{"form":"nimetini","tags":["accusative","definite","singular","third-person"]},{"form":"nimetlerini","tags":["accusative","definite","singular","third-person"]},{"form":"nimetimizi","tags":["accusative","definite","first-person","plural"]},{"form":"nimetlerimizi","tags":["accusative","definite","first-person","plural"]},{"form":"nimetinizi","tags":["accusative","definite","plural","second-person"]},{"form":"nimetlerinizi","tags":["accusative","definite","plural","second-person"]},{"form":"nimetlerini","tags":["accusative","definite","plural","third-person"]},{"form":"nimetime","tags":["dative","first-person","singular"]},{"form":"nimetlerime","tags":["dative","first-person","singular"]},{"form":"nimetine","tags":["dative","second-person","singular"]},{"form":"nimetlerine","tags":["dative","second-person","singular"]},{"form":"nimetine","tags":["dative","singular","third-person"]},{"form":"nimetlerine","tags":["dative","singular","third-person"]},{"form":"nimetimize","tags":["dative","first-person","plural"]},{"form":"nimetlerimize","tags":["dative","first-person","plural"]},{"form":"nimetinize","tags":["dative","plural","second-person"]},{"form":"nimetlerinize","tags":["dative","plural","second-person"]},{"form":"nimetlerine","tags":["dative","plural","third-person"]},{"form":"nimetimde","tags":["first-person","locative","singular"]},{"form":"nimetlerimde","tags":["first-person","locative","singular"]},{"form":"nimetinde","tags":["locative","second-person","singular"]},{"form":"nimetlerinde","tags":["locative","second-person","singular"]},{"form":"nimetinde","tags":["locative","singular","third-person"]},{"form":"nimetlerinde","tags":["locative","singular","third-person"]},{"form":"nimetimizde","tags":["first-person","locative","plural"]},{"form":"nimetlerimizde","tags":["first-person","locative","plural"]},{"form":"nimetinizde","tags":["locative","plural","second-person"]},{"form":"nimetlerinizde","tags":["locative","plural","second-person"]},{"form":"nimetlerinde","tags":["locative","plural","third-person"]},{"form":"nimetimden","tags":["ablative","first-person","singular"]},{"form":"nimetlerimden","tags":["ablative","first-person","singular"]},{"form":"nimetinden","tags":["ablative","second-person","singular"]},{"form":"nimetlerinden","tags":["ablative","second-person","singular"]},{"form":"nimetinden","tags":["ablative","singular","third-person"]},{"form":"nimetlerinden","tags":["ablative","singular","third-person"]},{"form":"nimetimizden","tags":["ablative","first-person","plural"]},{"form":"nimetlerimizden","tags":["ablative","first-person","plural"]},{"form":"nimetinizden","tags":["ablative","plural","second-person"]},{"form":"nimetlerinizden","tags":["ablative","plural","second-person"]},{"form":"nimetlerinden","tags":["ablative","plural","third-person"]},{"form":"nimetimin","tags":["first-person","genitive","singular"]},{"form":"nimetlerimin","tags":["first-person","genitive","singular"]},{"form":"nimetinin","tags":["genitive","second-person","singular"]},{"form":"nimetlerinin","tags":["genitive","second-person","singular"]},{"form":"nimetinin","tags":["genitive","singular","third-person"]},{"form":"nimetlerinin","tags":["genitive","singular","third-person"]},{"form":"nimetimizin","tags":["first-person","genitive","plural"]},{"form":"nimetlerimizin","tags":["first-person","genitive","plural"]},{"form":"nimetinizin","tags":["genitive","plural","second-person"]},{"form":"nimetlerinizin","tags":["genitive","plural","second-person"]},{"form":"nimetlerinin","tags":["genitive","plural","third-person"]}]}