{"word":"susama","pos":"noun","senses":[{"glosses":["verbal noun of susamak"],"tags":["form-of","noun-from-verb"]},{"glosses":["second-person singular negative imperative of susamak"],"tags":["form-of","imperative","negative","second-person","singular"]}],"forms":[{"form":"susamayı","tags":["accusative","definite"]},{"form":"susamalar","tags":["plural"]},{"form":"no-table-tags","tags":["table-tags"]},{"form":"tr-infl-noun-v","tags":["inflection-template"]},{"form":"susama","tags":["nominative","singular"]},{"form":"susamalar","tags":["nominative","plural"]},{"form":"susamayı","tags":["accusative","definite","singular"]},{"form":"susamaları","tags":["accusative","definite","plural"]},{"form":"susamaya","tags":["dative","singular"]},{"form":"susamalara","tags":["dative","plural"]},{"form":"susamada","tags":["locative","singular"]},{"form":"susamalarda","tags":["locative","plural"]},{"form":"susamadan","tags":["ablative","singular"]},{"form":"susamalardan","tags":["ablative","plural"]},{"form":"susamanın","tags":["genitive","singular"]},{"form":"susamaların","tags":["genitive","plural"]},{"form":"no-table-tags","tags":["table-tags"]},{"form":"tr-infl-noun-v","tags":["inflection-template"]},{"form":"susamam","tags":["first-person","nominative","singular"]},{"form":"susamalarım","tags":["first-person","nominative","singular"]},{"form":"susaman","tags":["nominative","second-person","singular"]},{"form":"susamaların","tags":["nominative","second-person","singular"]},{"form":"susaması","tags":["nominative","singular","third-person"]},{"form":"susamaları","tags":["nominative","singular","third-person"]},{"form":"susamamız","tags":["first-person","nominative","plural"]},{"form":"susamalarımız","tags":["first-person","nominative","plural"]},{"form":"susamanız","tags":["nominative","plural","second-person"]},{"form":"susamalarınız","tags":["nominative","plural","second-person"]},{"form":"susamaları","tags":["nominative","plural","third-person"]},{"form":"susamamı","tags":["accusative","definite","first-person","singular"]},{"form":"susamalarımı","tags":["accusative","definite","first-person","singular"]},{"form":"susamanı","tags":["accusative","definite","second-person","singular"]},{"form":"susamalarını","tags":["accusative","definite","second-person","singular"]},{"form":"susamasını","tags":["accusative","definite","singular","third-person"]},{"form":"susamalarını","tags":["accusative","definite","singular","third-person"]},{"form":"susamamızı","tags":["accusative","definite","first-person","plural"]},{"form":"susamalarımızı","tags":["accusative","definite","first-person","plural"]},{"form":"susamanızı","tags":["accusative","definite","plural","second-person"]},{"form":"susamalarınızı","tags":["accusative","definite","plural","second-person"]},{"form":"susamalarını","tags":["accusative","definite","plural","third-person"]},{"form":"susamama","tags":["dative","first-person","singular"]},{"form":"susamalarıma","tags":["dative","first-person","singular"]},{"form":"susamana","tags":["dative","second-person","singular"]},{"form":"susamalarına","tags":["dative","second-person","singular"]},{"form":"susamasına","tags":["dative","singular","third-person"]},{"form":"susamalarına","tags":["dative","singular","third-person"]},{"form":"susamamıza","tags":["dative","first-person","plural"]},{"form":"susamalarımıza","tags":["dative","first-person","plural"]},{"form":"susamanıza","tags":["dative","plural","second-person"]},{"form":"susamalarınıza","tags":["dative","plural","second-person"]},{"form":"susamalarına","tags":["dative","plural","third-person"]},{"form":"susamamda","tags":["first-person","locative","singular"]},{"form":"susamalarımda","tags":["first-person","locative","singular"]},{"form":"susamanda","tags":["locative","second-person","singular"]},{"form":"susamalarında","tags":["locative","second-person","singular"]},{"form":"susamasında","tags":["locative","singular","third-person"]},{"form":"susamalarında","tags":["locative","singular","third-person"]},{"form":"susamamızda","tags":["first-person","locative","plural"]},{"form":"susamalarımızda","tags":["first-person","locative","plural"]},{"form":"susamanızda","tags":["locative","plural","second-person"]},{"form":"susamalarınızda","tags":["locative","plural","second-person"]},{"form":"susamalarında","tags":["locative","plural","third-person"]},{"form":"susamamdan","tags":["ablative","first-person","singular"]},{"form":"susamalarımdan","tags":["ablative","first-person","singular"]},{"form":"susamandan","tags":["ablative","second-person","singular"]},{"form":"susamalarından","tags":["ablative","second-person","singular"]},{"form":"susamasından","tags":["ablative","singular","third-person"]},{"form":"susamalarından","tags":["ablative","singular","third-person"]},{"form":"susamamızdan","tags":["ablative","first-person","plural"]},{"form":"susamalarımızdan","tags":["ablative","first-person","plural"]},{"form":"susamanızdan","tags":["ablative","plural","second-person"]},{"form":"susamalarınızdan","tags":["ablative","plural","second-person"]},{"form":"susamalarından","tags":["ablative","plural","third-person"]},{"form":"susamamın","tags":["first-person","genitive","singular"]},{"form":"susamalarımın","tags":["first-person","genitive","singular"]},{"form":"susamanın","tags":["genitive","second-person","singular"]},{"form":"susamalarının","tags":["genitive","second-person","singular"]},{"form":"susamasının","tags":["genitive","singular","third-person"]},{"form":"susamalarının","tags":["genitive","singular","third-person"]},{"form":"susamamızın","tags":["first-person","genitive","plural"]},{"form":"susamalarımızın","tags":["first-person","genitive","plural"]},{"form":"susamanızın","tags":["genitive","plural","second-person"]},{"form":"susamalarınızın","tags":["genitive","plural","second-person"]},{"form":"susamalarının","tags":["genitive","plural","third-person"]}]}