{"word":"tanımlanma","pos":"noun","senses":[{"glosses":["verbal noun of tanımlanmak"],"tags":["form-of","noun-from-verb"]},{"glosses":["second-person singular negative imperative of tanımlanmak"],"tags":["form-of","imperative","negative","second-person","singular"]}],"forms":[{"form":"tanımlanmayı","tags":["accusative","definite"]},{"form":"tanımlanmalar","tags":["plural"]},{"form":"no-table-tags","tags":["table-tags"]},{"form":"tr-infl-noun-v","tags":["inflection-template"]},{"form":"tanımlanma","tags":["nominative","singular"]},{"form":"tanımlanmalar","tags":["nominative","plural"]},{"form":"tanımlanmayı","tags":["accusative","definite","singular"]},{"form":"tanımlanmaları","tags":["accusative","definite","plural"]},{"form":"tanımlanmaya","tags":["dative","singular"]},{"form":"tanımlanmalara","tags":["dative","plural"]},{"form":"tanımlanmada","tags":["locative","singular"]},{"form":"tanımlanmalarda","tags":["locative","plural"]},{"form":"tanımlanmadan","tags":["ablative","singular"]},{"form":"tanımlanmalardan","tags":["ablative","plural"]},{"form":"tanımlanmanın","tags":["genitive","singular"]},{"form":"tanımlanmaların","tags":["genitive","plural"]},{"form":"no-table-tags","tags":["table-tags"]},{"form":"tr-infl-noun-v","tags":["inflection-template"]},{"form":"tanımlanmam","tags":["first-person","nominative","singular"]},{"form":"tanımlanmalarım","tags":["first-person","nominative","singular"]},{"form":"tanımlanman","tags":["nominative","second-person","singular"]},{"form":"tanımlanmaların","tags":["nominative","second-person","singular"]},{"form":"tanımlanması","tags":["nominative","singular","third-person"]},{"form":"tanımlanmaları","tags":["nominative","singular","third-person"]},{"form":"tanımlanmamız","tags":["first-person","nominative","plural"]},{"form":"tanımlanmalarımız","tags":["first-person","nominative","plural"]},{"form":"tanımlanmanız","tags":["nominative","plural","second-person"]},{"form":"tanımlanmalarınız","tags":["nominative","plural","second-person"]},{"form":"tanımlanmaları","tags":["nominative","plural","third-person"]},{"form":"tanımlanmamı","tags":["accusative","definite","first-person","singular"]},{"form":"tanımlanmalarımı","tags":["accusative","definite","first-person","singular"]},{"form":"tanımlanmanı","tags":["accusative","definite","second-person","singular"]},{"form":"tanımlanmalarını","tags":["accusative","definite","second-person","singular"]},{"form":"tanımlanmasını","tags":["accusative","definite","singular","third-person"]},{"form":"tanımlanmalarını","tags":["accusative","definite","singular","third-person"]},{"form":"tanımlanmamızı","tags":["accusative","definite","first-person","plural"]},{"form":"tanımlanmalarımızı","tags":["accusative","definite","first-person","plural"]},{"form":"tanımlanmanızı","tags":["accusative","definite","plural","second-person"]},{"form":"tanımlanmalarınızı","tags":["accusative","definite","plural","second-person"]},{"form":"tanımlanmalarını","tags":["accusative","definite","plural","third-person"]},{"form":"tanımlanmama","tags":["dative","first-person","singular"]},{"form":"tanımlanmalarıma","tags":["dative","first-person","singular"]},{"form":"tanımlanmana","tags":["dative","second-person","singular"]},{"form":"tanımlanmalarına","tags":["dative","second-person","singular"]},{"form":"tanımlanmasına","tags":["dative","singular","third-person"]},{"form":"tanımlanmalarına","tags":["dative","singular","third-person"]},{"form":"tanımlanmamıza","tags":["dative","first-person","plural"]},{"form":"tanımlanmalarımıza","tags":["dative","first-person","plural"]},{"form":"tanımlanmanıza","tags":["dative","plural","second-person"]},{"form":"tanımlanmalarınıza","tags":["dative","plural","second-person"]},{"form":"tanımlanmalarına","tags":["dative","plural","third-person"]},{"form":"tanımlanmamda","tags":["first-person","locative","singular"]},{"form":"tanımlanmalarımda","tags":["first-person","locative","singular"]},{"form":"tanımlanmanda","tags":["locative","second-person","singular"]},{"form":"tanımlanmalarında","tags":["locative","second-person","singular"]},{"form":"tanımlanmasında","tags":["locative","singular","third-person"]},{"form":"tanımlanmalarında","tags":["locative","singular","third-person"]},{"form":"tanımlanmamızda","tags":["first-person","locative","plural"]},{"form":"tanımlanmalarımızda","tags":["first-person","locative","plural"]},{"form":"tanımlanmanızda","tags":["locative","plural","second-person"]},{"form":"tanımlanmalarınızda","tags":["locative","plural","second-person"]},{"form":"tanımlanmalarında","tags":["locative","plural","third-person"]},{"form":"tanımlanmamdan","tags":["ablative","first-person","singular"]},{"form":"tanımlanmalarımdan","tags":["ablative","first-person","singular"]},{"form":"tanımlanmandan","tags":["ablative","second-person","singular"]},{"form":"tanımlanmalarından","tags":["ablative","second-person","singular"]},{"form":"tanımlanmasından","tags":["ablative","singular","third-person"]},{"form":"tanımlanmalarından","tags":["ablative","singular","third-person"]},{"form":"tanımlanmamızdan","tags":["ablative","first-person","plural"]},{"form":"tanımlanmalarımızdan","tags":["ablative","first-person","plural"]},{"form":"tanımlanmanızdan","tags":["ablative","plural","second-person"]},{"form":"tanımlanmalarınızdan","tags":["ablative","plural","second-person"]},{"form":"tanımlanmalarından","tags":["ablative","plural","third-person"]},{"form":"tanımlanmamın","tags":["first-person","genitive","singular"]},{"form":"tanımlanmalarımın","tags":["first-person","genitive","singular"]},{"form":"tanımlanmanın","tags":["genitive","second-person","singular"]},{"form":"tanımlanmalarının","tags":["genitive","second-person","singular"]},{"form":"tanımlanmasının","tags":["genitive","singular","third-person"]},{"form":"tanımlanmalarının","tags":["genitive","singular","third-person"]},{"form":"tanımlanmamızın","tags":["first-person","genitive","plural"]},{"form":"tanımlanmalarımızın","tags":["first-person","genitive","plural"]},{"form":"tanımlanmanızın","tags":["genitive","plural","second-person"]},{"form":"tanımlanmalarınızın","tags":["genitive","plural","second-person"]},{"form":"tanımlanmalarının","tags":["genitive","plural","third-person"]}]}