{"word":"ufuk","pos":"noun","senses":[{"glosses":["horizon"]},{"glosses":["a male given name from Arabic"]},{"glosses":["a female given name from Arabic"]}],"etymology":"From Ottoman Turkish افق, from Arabic أُفُق (ʔufuq).","forms":[{"form":"ufku","tags":["accusative","definite"]},{"form":"ufuklar","tags":["plural"]},{"form":"no-table-tags","tags":["table-tags"]},{"form":"tr-infl-noun-c","tags":["inflection-template"]},{"form":"ufuk","tags":["nominative","singular"]},{"form":"ufuklar","tags":["nominative","plural"]},{"form":"ufku","tags":["accusative","definite","singular"]},{"form":"ufukları","tags":["accusative","definite","plural"]},{"form":"ufka","tags":["dative","singular"]},{"form":"ufuklara","tags":["dative","plural"]},{"form":"ufukta","tags":["locative","singular"]},{"form":"ufuklarda","tags":["locative","plural"]},{"form":"ufuktan","tags":["ablative","singular"]},{"form":"ufuklardan","tags":["ablative","plural"]},{"form":"ufkun","tags":["genitive","singular"]},{"form":"ufukların","tags":["genitive","plural"]},{"form":"no-table-tags","tags":["table-tags"]},{"form":"tr-infl-noun-c","tags":["inflection-template"]},{"form":"ufkum","tags":["first-person","nominative","singular"]},{"form":"ufuklarım","tags":["first-person","nominative","singular"]},{"form":"ufkun","tags":["nominative","second-person","singular"]},{"form":"ufukların","tags":["nominative","second-person","singular"]},{"form":"ufku","tags":["nominative","singular","third-person"]},{"form":"ufukları","tags":["nominative","singular","third-person"]},{"form":"ufkumuz","tags":["first-person","nominative","plural"]},{"form":"ufuklarımız","tags":["first-person","nominative","plural"]},{"form":"ufkunuz","tags":["nominative","plural","second-person"]},{"form":"ufuklarınız","tags":["nominative","plural","second-person"]},{"form":"ufukları","tags":["nominative","plural","third-person"]},{"form":"ufkumu","tags":["accusative","definite","first-person","singular"]},{"form":"ufuklarımı","tags":["accusative","definite","first-person","singular"]},{"form":"ufkunu","tags":["accusative","definite","second-person","singular"]},{"form":"ufuklarını","tags":["accusative","definite","second-person","singular"]},{"form":"ufkunu","tags":["accusative","definite","singular","third-person"]},{"form":"ufuklarını","tags":["accusative","definite","singular","third-person"]},{"form":"ufkumuzu","tags":["accusative","definite","first-person","plural"]},{"form":"ufuklarımızı","tags":["accusative","definite","first-person","plural"]},{"form":"ufkunuzu","tags":["accusative","definite","plural","second-person"]},{"form":"ufuklarınızı","tags":["accusative","definite","plural","second-person"]},{"form":"ufuklarını","tags":["accusative","definite","plural","third-person"]},{"form":"ufkuma","tags":["dative","first-person","singular"]},{"form":"ufuklarıma","tags":["dative","first-person","singular"]},{"form":"ufkuna","tags":["dative","second-person","singular"]},{"form":"ufuklarına","tags":["dative","second-person","singular"]},{"form":"ufkuna","tags":["dative","singular","third-person"]},{"form":"ufuklarına","tags":["dative","singular","third-person"]},{"form":"ufkumuza","tags":["dative","first-person","plural"]},{"form":"ufuklarımıza","tags":["dative","first-person","plural"]},{"form":"ufkunuza","tags":["dative","plural","second-person"]},{"form":"ufuklarınıza","tags":["dative","plural","second-person"]},{"form":"ufuklarına","tags":["dative","plural","third-person"]},{"form":"ufkumda","tags":["first-person","locative","singular"]},{"form":"ufuklarımda","tags":["first-person","locative","singular"]},{"form":"ufkunda","tags":["locative","second-person","singular"]},{"form":"ufuklarında","tags":["locative","second-person","singular"]},{"form":"ufkunda","tags":["locative","singular","third-person"]},{"form":"ufuklarında","tags":["locative","singular","third-person"]},{"form":"ufkumuzda","tags":["first-person","locative","plural"]},{"form":"ufuklarımızda","tags":["first-person","locative","plural"]},{"form":"ufkunuzda","tags":["locative","plural","second-person"]},{"form":"ufuklarınızda","tags":["locative","plural","second-person"]},{"form":"ufuklarında","tags":["locative","plural","third-person"]},{"form":"ufkumdan","tags":["ablative","first-person","singular"]},{"form":"ufuklarımdan","tags":["ablative","first-person","singular"]},{"form":"ufkundan","tags":["ablative","second-person","singular"]},{"form":"ufuklarından","tags":["ablative","second-person","singular"]},{"form":"ufkundan","tags":["ablative","singular","third-person"]},{"form":"ufuklarından","tags":["ablative","singular","third-person"]},{"form":"ufkumuzdan","tags":["ablative","first-person","plural"]},{"form":"ufuklarımızdan","tags":["ablative","first-person","plural"]},{"form":"ufkunuzdan","tags":["ablative","plural","second-person"]},{"form":"ufuklarınızdan","tags":["ablative","plural","second-person"]},{"form":"ufuklarından","tags":["ablative","plural","third-person"]},{"form":"ufkumun","tags":["first-person","genitive","singular"]},{"form":"ufuklarımın","tags":["first-person","genitive","singular"]},{"form":"ufkunun","tags":["genitive","second-person","singular"]},{"form":"ufuklarının","tags":["genitive","second-person","singular"]},{"form":"ufkunun","tags":["genitive","singular","third-person"]},{"form":"ufuklarının","tags":["genitive","singular","third-person"]},{"form":"ufkumuzun","tags":["first-person","genitive","plural"]},{"form":"ufuklarımızın","tags":["first-person","genitive","plural"]},{"form":"ufkunuzun","tags":["genitive","plural","second-person"]},{"form":"ufuklarınızın","tags":["genitive","plural","second-person"]},{"form":"ufuklarının","tags":["genitive","plural","third-person"]},{"form":"no-table-tags","tags":["table-tags"]},{"form":"tr-infl-noun-c","tags":["inflection-template"]},{"form":"ufkum","tags":["first-person","singular"]},{"form":"ufuklarım","tags":["first-person","singular"]},{"form":"ufuksun","tags":["second-person","singular"]},{"form":"ufuklarsın","tags":["second-person","singular"]},{"form":"ufuk","tags":["singular","third-person"]},{"form":"ufuktur","tags":["singular","third-person"]},{"form":"ufuklar","tags":["singular","third-person"]},{"form":"ufuklardır","tags":["singular","third-person"]},{"form":"ufkuz","tags":["first-person","plural"]},{"form":"ufuklarız","tags":["first-person","plural"]},{"form":"ufuksunuz","tags":["plural","second-person"]},{"form":"ufuklarsınız","tags":["plural","second-person"]},{"form":"ufuklar","tags":["plural","third-person"]},{"form":"ufuklardır","tags":["plural","third-person"]}]}