{"word":"yıldız","pos":"noun","senses":[{"glosses":["star"],"examples":[{"text":"Güneş Dünya'ya en yakın yıldızdır","translation":"The Sun is the closest star to the Earth"}]},{"glosses":["An exceptionally talented or famous person, often in a specific field, locally or otherwise; a celebrity, a star"]},{"glosses":["Actors in leading roles in movies, television shows and other dramatic media, a star"]},{"glosses":["An asterisk (*)."],"examples":[{"text":"Proto-diller herhangi bir yazılı kaynakta geçmedikleri için kelimeler yeniden yapılandırılırken yıldız konur.","translation":"Since proto-languages are not directly attested in any written sources, asterisks are used while reconstruction."}]},{"glosses":["A symbol used to rate quality, notably used for hotels, with ratings from 1 (poor quality) to 5 stars (top quality)"],"examples":[{"text":"5 yıldızlı otel","translation":"a 5-star otel"}]},{"glosses":["luck"],"synonyms":["şans","talih","baht"]},{"glosses":["north"],"tags":["uncommon"],"synonyms":["kuzey"]},{"glosses":["an eye of a needle"],"tags":["Niğde"]},{"glosses":["a female given name"]},{"glosses":["a surname"]},{"glosses":["Name of a palace in Istanbul of Sultan Abdulhamid II."]}],"pronunciation":"/jɯɫ.ˈdɯz/","etymology":"From Ottoman Turkish یلدز (yıldız), from Old Anatolian Turkish یلدز (yılduz, yulduz), from Proto-Turkic *yulduŕ (“star”), see there for more.","forms":[{"form":"yıldızı","tags":["accusative","definite"]},{"form":"yıldızlar","tags":["plural"]},{"form":"no-table-tags","tags":["table-tags"]},{"form":"tr-infl-noun-c","tags":["inflection-template"]},{"form":"yıldız","tags":["nominative","singular"]},{"form":"yıldızlar","tags":["nominative","plural"]},{"form":"yıldızı","tags":["accusative","definite","singular"]},{"form":"yıldızları","tags":["accusative","definite","plural"]},{"form":"yıldıza","tags":["dative","singular"]},{"form":"yıldızlara","tags":["dative","plural"]},{"form":"yıldızda","tags":["locative","singular"]},{"form":"yıldızlarda","tags":["locative","plural"]},{"form":"yıldızdan","tags":["ablative","singular"]},{"form":"yıldızlardan","tags":["ablative","plural"]},{"form":"yıldızın","tags":["genitive","singular"]},{"form":"yıldızların","tags":["genitive","plural"]},{"form":"no-table-tags","tags":["table-tags"]},{"form":"tr-infl-noun-c","tags":["inflection-template"]},{"form":"yıldızım","tags":["first-person","nominative","singular"]},{"form":"yıldızlarım","tags":["first-person","nominative","singular"]},{"form":"yıldızın","tags":["nominative","second-person","singular"]},{"form":"yıldızların","tags":["nominative","second-person","singular"]},{"form":"yıldızı","tags":["nominative","singular","third-person"]},{"form":"yıldızları","tags":["nominative","singular","third-person"]},{"form":"yıldızımız","tags":["first-person","nominative","plural"]},{"form":"yıldızlarımız","tags":["first-person","nominative","plural"]},{"form":"yıldızınız","tags":["nominative","plural","second-person"]},{"form":"yıldızlarınız","tags":["nominative","plural","second-person"]},{"form":"yıldızları","tags":["nominative","plural","third-person"]},{"form":"yıldızımı","tags":["accusative","definite","first-person","singular"]},{"form":"yıldızlarımı","tags":["accusative","definite","first-person","singular"]},{"form":"yıldızını","tags":["accusative","definite","second-person","singular"]},{"form":"yıldızlarını","tags":["accusative","definite","second-person","singular"]},{"form":"yıldızını","tags":["accusative","definite","singular","third-person"]},{"form":"yıldızlarını","tags":["accusative","definite","singular","third-person"]},{"form":"yıldızımızı","tags":["accusative","definite","first-person","plural"]},{"form":"yıldızlarımızı","tags":["accusative","definite","first-person","plural"]},{"form":"yıldızınızı","tags":["accusative","definite","plural","second-person"]},{"form":"yıldızlarınızı","tags":["accusative","definite","plural","second-person"]},{"form":"yıldızlarını","tags":["accusative","definite","plural","third-person"]},{"form":"yıldızıma","tags":["dative","first-person","singular"]},{"form":"yıldızlarıma","tags":["dative","first-person","singular"]},{"form":"yıldızına","tags":["dative","second-person","singular"]},{"form":"yıldızlarına","tags":["dative","second-person","singular"]},{"form":"yıldızına","tags":["dative","singular","third-person"]},{"form":"yıldızlarına","tags":["dative","singular","third-person"]},{"form":"yıldızımıza","tags":["dative","first-person","plural"]},{"form":"yıldızlarımıza","tags":["dative","first-person","plural"]},{"form":"yıldızınıza","tags":["dative","plural","second-person"]},{"form":"yıldızlarınıza","tags":["dative","plural","second-person"]},{"form":"yıldızlarına","tags":["dative","plural","third-person"]},{"form":"yıldızımda","tags":["first-person","locative","singular"]},{"form":"yıldızlarımda","tags":["first-person","locative","singular"]},{"form":"yıldızında","tags":["locative","second-person","singular"]},{"form":"yıldızlarında","tags":["locative","second-person","singular"]},{"form":"yıldızında","tags":["locative","singular","third-person"]},{"form":"yıldızlarında","tags":["locative","singular","third-person"]},{"form":"yıldızımızda","tags":["first-person","locative","plural"]},{"form":"yıldızlarımızda","tags":["first-person","locative","plural"]},{"form":"yıldızınızda","tags":["locative","plural","second-person"]},{"form":"yıldızlarınızda","tags":["locative","plural","second-person"]},{"form":"yıldızlarında","tags":["locative","plural","third-person"]},{"form":"yıldızımdan","tags":["ablative","first-person","singular"]},{"form":"yıldızlarımdan","tags":["ablative","first-person","singular"]},{"form":"yıldızından","tags":["ablative","second-person","singular"]},{"form":"yıldızlarından","tags":["ablative","second-person","singular"]},{"form":"yıldızından","tags":["ablative","singular","third-person"]},{"form":"yıldızlarından","tags":["ablative","singular","third-person"]},{"form":"yıldızımızdan","tags":["ablative","first-person","plural"]},{"form":"yıldızlarımızdan","tags":["ablative","first-person","plural"]},{"form":"yıldızınızdan","tags":["ablative","plural","second-person"]},{"form":"yıldızlarınızdan","tags":["ablative","plural","second-person"]},{"form":"yıldızlarından","tags":["ablative","plural","third-person"]},{"form":"yıldızımın","tags":["first-person","genitive","singular"]},{"form":"yıldızlarımın","tags":["first-person","genitive","singular"]},{"form":"yıldızının","tags":["genitive","second-person","singular"]},{"form":"yıldızlarının","tags":["genitive","second-person","singular"]},{"form":"yıldızının","tags":["genitive","singular","third-person"]},{"form":"yıldızlarının","tags":["genitive","singular","third-person"]},{"form":"yıldızımızın","tags":["first-person","genitive","plural"]},{"form":"yıldızlarımızın","tags":["first-person","genitive","plural"]},{"form":"yıldızınızın","tags":["genitive","plural","second-person"]},{"form":"yıldızlarınızın","tags":["genitive","plural","second-person"]},{"form":"yıldızlarının","tags":["genitive","plural","third-person"]}]}