{"word":"yeme","pos":"noun","senses":[{"glosses":["verbal noun of yemek"],"tags":["form-of","noun-from-verb"]},{"glosses":["food"]},{"glosses":["second-person singular negative imperative of yemek"],"tags":["form-of","imperative","negative","second-person","singular"]}],"forms":[{"form":"yemeyi","tags":["accusative","definite"]},{"form":"yemeler","tags":["plural"]},{"form":"no-table-tags","tags":["table-tags"]},{"form":"tr-infl-noun-v","tags":["inflection-template"]},{"form":"yeme","tags":["nominative","singular"]},{"form":"yemeler","tags":["nominative","plural"]},{"form":"yemeyi","tags":["accusative","definite","singular"]},{"form":"yemeleri","tags":["accusative","definite","plural"]},{"form":"yemeye","tags":["dative","singular"]},{"form":"yemelere","tags":["dative","plural"]},{"form":"yemede","tags":["locative","singular"]},{"form":"yemelerde","tags":["locative","plural"]},{"form":"yemeden","tags":["ablative","singular"]},{"form":"yemelerden","tags":["ablative","plural"]},{"form":"yemenin","tags":["genitive","singular"]},{"form":"yemelerin","tags":["genitive","plural"]},{"form":"no-table-tags","tags":["table-tags"]},{"form":"tr-infl-noun-v","tags":["inflection-template"]},{"form":"yemem","tags":["first-person","nominative","singular"]},{"form":"yemelerim","tags":["first-person","nominative","singular"]},{"form":"yemen","tags":["nominative","second-person","singular"]},{"form":"yemelerin","tags":["nominative","second-person","singular"]},{"form":"yemesi","tags":["nominative","singular","third-person"]},{"form":"yemeleri","tags":["nominative","singular","third-person"]},{"form":"yememiz","tags":["first-person","nominative","plural"]},{"form":"yemelerimiz","tags":["first-person","nominative","plural"]},{"form":"yemeniz","tags":["nominative","plural","second-person"]},{"form":"yemeleriniz","tags":["nominative","plural","second-person"]},{"form":"yemeleri","tags":["nominative","plural","third-person"]},{"form":"yememi","tags":["accusative","definite","first-person","singular"]},{"form":"yemelerimi","tags":["accusative","definite","first-person","singular"]},{"form":"yemeni","tags":["accusative","definite","second-person","singular"]},{"form":"yemelerini","tags":["accusative","definite","second-person","singular"]},{"form":"yemesini","tags":["accusative","definite","singular","third-person"]},{"form":"yemelerini","tags":["accusative","definite","singular","third-person"]},{"form":"yememizi","tags":["accusative","definite","first-person","plural"]},{"form":"yemelerimizi","tags":["accusative","definite","first-person","plural"]},{"form":"yemenizi","tags":["accusative","definite","plural","second-person"]},{"form":"yemelerinizi","tags":["accusative","definite","plural","second-person"]},{"form":"yemelerini","tags":["accusative","definite","plural","third-person"]},{"form":"yememe","tags":["dative","first-person","singular"]},{"form":"yemelerime","tags":["dative","first-person","singular"]},{"form":"yemene","tags":["dative","second-person","singular"]},{"form":"yemelerine","tags":["dative","second-person","singular"]},{"form":"yemesine","tags":["dative","singular","third-person"]},{"form":"yemelerine","tags":["dative","singular","third-person"]},{"form":"yememize","tags":["dative","first-person","plural"]},{"form":"yemelerimize","tags":["dative","first-person","plural"]},{"form":"yemenize","tags":["dative","plural","second-person"]},{"form":"yemelerinize","tags":["dative","plural","second-person"]},{"form":"yemelerine","tags":["dative","plural","third-person"]},{"form":"yememde","tags":["first-person","locative","singular"]},{"form":"yemelerimde","tags":["first-person","locative","singular"]},{"form":"yemende","tags":["locative","second-person","singular"]},{"form":"yemelerinde","tags":["locative","second-person","singular"]},{"form":"yemesinde","tags":["locative","singular","third-person"]},{"form":"yemelerinde","tags":["locative","singular","third-person"]},{"form":"yememizde","tags":["first-person","locative","plural"]},{"form":"yemelerimizde","tags":["first-person","locative","plural"]},{"form":"yemenizde","tags":["locative","plural","second-person"]},{"form":"yemelerinizde","tags":["locative","plural","second-person"]},{"form":"yemelerinde","tags":["locative","plural","third-person"]},{"form":"yememden","tags":["ablative","first-person","singular"]},{"form":"yemelerimden","tags":["ablative","first-person","singular"]},{"form":"yemenden","tags":["ablative","second-person","singular"]},{"form":"yemelerinden","tags":["ablative","second-person","singular"]},{"form":"yemesinden","tags":["ablative","singular","third-person"]},{"form":"yemelerinden","tags":["ablative","singular","third-person"]},{"form":"yememizden","tags":["ablative","first-person","plural"]},{"form":"yemelerimizden","tags":["ablative","first-person","plural"]},{"form":"yemenizden","tags":["ablative","plural","second-person"]},{"form":"yemelerinizden","tags":["ablative","plural","second-person"]},{"form":"yemelerinden","tags":["ablative","plural","third-person"]},{"form":"yememin","tags":["first-person","genitive","singular"]},{"form":"yemelerimin","tags":["first-person","genitive","singular"]},{"form":"yemenin","tags":["genitive","second-person","singular"]},{"form":"yemelerinin","tags":["genitive","second-person","singular"]},{"form":"yemesinin","tags":["genitive","singular","third-person"]},{"form":"yemelerinin","tags":["genitive","singular","third-person"]},{"form":"yememizin","tags":["first-person","genitive","plural"]},{"form":"yemelerimizin","tags":["first-person","genitive","plural"]},{"form":"yemenizin","tags":["genitive","plural","second-person"]},{"form":"yemelerinizin","tags":["genitive","plural","second-person"]},{"form":"yemelerinin","tags":["genitive","plural","third-person"]}]}